[
  {
    "key": 1,
    "title": "Food App",
    "imageSrc": "https://blog.digimarkland.com/wp-content/uploads/2023/03/AI-Food-App.png",
    "description": "This is a project made with complete React js , MongoDb , Node Js , Express Js.",
    "source": "https://github.com/nerdyawedee/Food_App/tree/main"
  },
  {
    "key": 2,
    "title": "Mern Blogging",
    "imageSrc": "https://tse3.mm.bing.net/th?id=OIP.XG44bglJYw1IgQdrR-ehAwHaHW&pid=Api&P=0&h=180",
    "description": "This is a project made with complete React Js , Mern JS ,Firebase, Node Js , Express Js ,.",
    "source": "https://github.com/nerdyawedee/Mern-Blog/tree/main"
  },
  {
    "key": 3,
    "title": "PortFolio",
    "imageSrc": "https://tse3.mm.bing.net/th?id=OIP.UKQTqcuclH5azTtQUoI_-QHaE8&pid=Api&P=0&h=180",
    "description": "This is a project made with complete React js. Bootstrap , Javascript",
    "source": "https://github.com/nerdyawedee/Portfolio/tree/main"
  }
]
